arte/__init__.py
arte/__version__.py
arte/code_convention.py
arte/atmo/__init__.py
arte/atmo/abstract_phase_screen_generator.py
arte/atmo/cn2_profile.py
arte/atmo/phase_screen_generator.py
arte/atmo/utils.py
arte/atmo/von_karman_covariance_calculator.py
arte/atmo/von_karman_psd.py
arte/atmo/von_karman_spatial_covariance_calculator.py
arte/contrib/__init__.py
arte/contrib/chunk_iterator.py
arte/contrib/daemonize.py
arte/contrib/debug.py
arte/contrib/if_.py
arte/contrib/interpolated_array.py
arte/contrib/timer.py
arte/contrib/yes_no.py
arte/control/__init__.py
arte/control/transfer_function.py
arte/data/cn2profiles/cn2_eso_258292_2.fits
arte/data/cn2profiles/maoryPProfiles.fits
arte/data/cn2profiles/referenceProfiles35layers.fits
arte/data/cn2profiles/referenceProfiles35layers_new.fits
arte/data/cn2profiles/referenceWindProfiles35layers.fits
arte/data/photometry/detectors/c_red_one.dat
arte/data/photometry/detectors/ccd220.dat
arte/data/photometry/filters/bessell90/bessell90_i.dat
arte/data/photometry/filters/bessell90/bessell90_r.dat
arte/data/photometry/filters/eso_etc/phot_b.dat
arte/data/photometry/filters/eso_etc/phot_h.dat
arte/data/photometry/filters/eso_etc/phot_i.dat
arte/data/photometry/filters/eso_etc/phot_j.dat
arte/data/photometry/filters/eso_etc/phot_k.dat
arte/data/photometry/filters/eso_etc/phot_l.dat
arte/data/photometry/filters/eso_etc/phot_m.dat
arte/data/photometry/filters/eso_etc/phot_n.dat
arte/data/photometry/filters/eso_etc/phot_q.dat
arte/data/photometry/filters/eso_etc/phot_r.dat
arte/data/photometry/filters/eso_etc/phot_u.dat
arte/data/photometry/filters/eso_etc/phot_v.dat
arte/data/photometry/filters/eso_etc/phot_y.dat
arte/data/photometry/filters/eso_etc/phot_z.dat
arte/data/photometry/spectra/sp_K5V_norm_R0_ESO.fits
arte/data/photometry/spectra/vega_k93_array.fits
arte/data/photometry/transmissive_elements/coated_glasses/infrasil_1mm_B_coated_001/t.dat
arte-0.23.0.dist-info/licenses/LICENSE
arte-0.23.0.dist-info/METADATA
arte-0.23.0.dist-info/WHEEL
arte-0.23.0.dist-info/top_level.txt
arte-0.23.0.dist-info/RECORD
