Metadata-Version: 2.4
Name: arte
Version: 0.23.0
Summary: Arcetri Random sTuff collEction
Home-page: https://github.com/ArcetriAdaptiveOptics/arte
Author: Lorenzo Busoni, Alfio Puglisi, INAF Arcetri Adaptive Optics group
Author-email: lorenzo.busoni@inaf.it
License: MIT
Keywords: Adaptive Optics, Astrophysics, INAF, Arcetri
Classifier: Development Status :: 4 - Beta
Classifier: Operating System :: POSIX :: Linux
Classifier: Programming Language :: Python :: 3
Requires-Python: >=3.8.0
License-File: LICENSE
Requires-Dist: numpy>1.17
Requires-Dist: scipy
Requires-Dist: matplotlib
Requires-Dist: astropy
Requires-Dist: synphot
Requires-Dist: pytest
Requires-Dist: skycalc-cli
Requires-Dist: scikit-image>=0.17
Requires-Dist: scipy
Requires-Dist: mpmath
Requires-Dist: requests
Dynamic: author
Dynamic: author-email
Dynamic: classifier
Dynamic: description
Dynamic: home-page
Dynamic: keywords
Dynamic: license
Dynamic: license-file
Dynamic: requires-dist
Dynamic: requires-python
Dynamic: summary
